Metadata-Version: 2.4
Name: otlmow_converter
Version: 1.16
Author-email: David Vlaminck <david.vlaminck@mow.vlaanderen.be>
License:                     GNU GENERAL PUBLIC LICENSE
Project-URL: Homepage, https://github.com/davidvlaminck/OTLMOW-Converter
Project-URL: Bug Tracker, https://github.com/davidvlaminck/OTLMOW-Converter/issues
Classifier: Programming Language :: Python :: 3
Classifier: Programming Language :: Python :: 3.9
Classifier: Programming Language :: Python :: 3.10
Classifier: Programming Language :: Python :: 3.11
Classifier: Programming Language :: Python :: 3.12
Classifier: Programming Language :: Python :: 3.13
Classifier: Programming Language :: Python :: 3.14
Classifier: Operating System :: OS Independent
Requires-Python: >=3.9
License-File: LICENSE
Requires-Dist: openpyxl>=3.0
Requires-Dist: otlmow-model>=2.15.7.0
Requires-Dist: rdflib>=6.0.0
Requires-Dist: geojson>=3.0.1
Requires-Dist: prettytable>=3.6.0
Requires-Dist: lxml>=4.9.3
Requires-Dist: pandas>=1.3.5
Requires-Dist: pyarrow>=12.0.0
Provides-Extra: test
Requires-Dist: pytest; extra == "test"
Requires-Dist: pytest-cov; extra == "test"
Requires-Dist: pytest-subtests; extra == "test"
Requires-Dist: pytest-timeout; extra == "test"
Requires-Dist: pytest-asyncio; extra == "test"
Requires-Dist: nbmake; extra == "test"
Provides-Extra: benchmark
Requires-Dist: prettytable; extra == "benchmark"
Dynamic: license-file
